wisbec/__init__.py
wisbec/algorithm/__init__.py
wisbec/android/__init__.py
wisbec/android/aapt.py
wisbec/android/adb.py
wisbec/android/apk.py
wisbec/concurrency/__init__.py
wisbec/concurrency/thread_pool.py
wisbec/console/__init__.py
wisbec/console/shell.py
wisbec/crypto/__init__.py
wisbec/crypto/hash.py
wisbec/database/__init__.py
wisbec/database/db.py
wisbec/date/__init__.py
wisbec/date/time.py
wisbec/decorator/__init__.py
wisbec/design_patterns/__init__.py
wisbec/design_patterns/singleton.py
wisbec/feature_extend/__init__.py
wisbec/feature_extend/const.py
wisbec/file/__init__.py
wisbec/file/file.py
wisbec/file/zip.py
wisbec/filesystem/__init__.py
wisbec/filesystem/filesystem.py
wisbec/logging/__init__.py
wisbec/logging/log.py
wisbec/network/__init__.py
wisbec/network/interface.py
wisbec/network/url.py
wisbec/parser/__init__.py
wisbec/parser/parse.py
wisbec/path/__init__.py
wisbec/resource/__init__.py
wisbec/resource/resource.py
wisbec/resource/installation_pkg/android-tool.apk
wisbec/shell_parser/__init__.py
wisbec/shell_parser/ps.py
wisbec/shell_parser/model/__init__.py
wisbec/shell_parser/model/ps_info.py
wisbec/system/__init__.py
wisbec-0.5.0.dist-info/LICENSE
wisbec-0.5.0.dist-info/METADATA
wisbec-0.5.0.dist-info/WHEEL
wisbec-0.5.0.dist-info/top_level.txt
wisbec-0.5.0.dist-info/RECORD
