Metadata-Version: 2.1
Name: wisbec
Version: 0.5.0
Summary: python wrappers
Home-page: https://github.com/Future-Walkers/python-mod
Author: rodneycheung
Author-email: jsrdzhk@gmail.com
License: MIT License
Requires-Dist: sshtunnel
Requires-Dist: pymysql
Requires-Dist: colorlog
Requires-Dist: DBUtils
Requires-Dist: tldextract
